{"data":{"filteredRemarkPosts":null,"filteredQiitaPosts":{"edges":[{"node":{"fields":{"slug":"/41febdc6-bf5d-50b8-a695-3c017b8f766a/","title":"10分でできる！ @ngrx/storeチュートリアル with @ngrx/schematics","excerpt":"なにこれAngularで状態管理する方法をざっくり把握するためのチュートリアルです。@ngrx/storeベースの簡単なアプリ（数をカウントするアプリ）を作成します。作るだけなら10分程度で出来上がるので、とりあえず手を動かしてngrxを最...","date":"2018-07-30T18:01:02+09:00","tags":["Angular","angular-cli","ngrx","Angular6","Qiita"]}}}]},"allRemarkTags":{"edges":[{"node":{"fields":{"tags":["Gatsby","PWA"]}}},{"node":{"fields":{"tags":["Gatsby","SNS","SER"]}}},{"node":{"fields":{"tags":["Gatsby","React","CSSModules"]}}},{"node":{"fields":{"tags":["Vim","Vimium"]}}},{"node":{"fields":{"tags":["mdx-deck","mdx","code-surfer","markdown","プレゼン","スライド"]}}},{"node":{"fields":{"tags":["Gatsby","ブログ"]}}},{"node":{"fields":{"tags":["パソコン","肩こり","キーボード","デュアルキーボード"]}}},{"node":{"fields":{"tags":["Gatsby","ブログ"]}}},{"node":{"fields":{"tags":["Github-Pages","カスタムドメイン","Https化","Gatsby"]}}},{"node":{"fields":{"tags":["Git","GitHub","読書感想"]}}},{"node":{"fields":{"tags":["GraphQL","Nuxt.js","Apollo Client","Vue.js","読書感想"]}}},{"node":{"fields":{"tags":["JavaScript","mdx-deck","勉強会","LT"]}}},{"node":{"fields":{"tags":["Gatsby"]}}},{"node":{"fields":{"tags":["Gatsby","GatsbyPlugin"]}}},{"node":{"fields":{"tags":["Vue.js","Vuetify"]}}},{"node":{"fields":{"tags":["Vue.js","Vuetify","VeeValidate","VueI18n"]}}},{"node":{"fields":{"tags":["Vuetify","Vue.js"]}}},{"node":{"fields":{"tags":["Vue.js","VueI18n"]}}},{"node":{"fields":{"tags":["Vue.js","Vuetify","VeeValidate","VueI18n"]}}},{"node":{"fields":{"tags":["Amplify","AppSync","AWS","Cognito"]}}},{"node":{"fields":{"tags":["Vue.js","Vuetify","Vuex"]}}},{"node":{"fields":{"tags":["Gatsby"]}}},{"node":{"fields":{"tags":["Gatsby","gatsby-image"]}}},{"node":{"fields":{"tags":["Gatsby"]}}},{"node":{"fields":{"tags":["勉強会"]}}},{"node":{"fields":{"tags":["Gatsby","gatsy-image"]}}},{"node":{"fields":{"tags":["Gatsby","Cytoscape.js"]}}},{"node":{"fields":{"tags":["Gatsby"]}}},{"node":{"fields":{"tags":["Gatsby","GatsbyPlugin"]}}},{"node":{"fields":{"tags":["CSS","clip-path","React"]}}},{"node":{"fields":{"tags":["React","unified","remark","rehype"]}}},{"node":{"fields":{"tags":["Gatsby","React","OGP","SNS","SRE"]}}},{"node":{"fields":{"tags":["React","Schema-org","JSON-LD","SRE"]}}},{"node":{"fields":{"tags":["GraphQL","Graphpack"]}}},{"node":{"fields":{"tags":["Iframely","oEmbed","埋め込みコード","React","Gatsby"]}}},{"node":{"fields":{"tags":["Gatsby","GatsbyPlugin","Qiita"]}}},{"node":{"fields":{"tags":["AppSync","serverless","AWS","GraphQL"]}}},{"node":{"fields":{"tags":["AppSync","AWS","Cognito"]}}},{"node":{"fields":{"tags":["AppSync","AWS","GraphQL","DynamoDB"]}}},{"node":{"fields":{"tags":["Gatsby","Hugo","golang"]}}},{"node":{"fields":{"tags":["AppSync","AWS","GraphQL"]}}},{"node":{"fields":{"tags":["Netlify","NetlifyForms","React","Fromik","Axios"]}}},{"node":{"fields":{"tags":["Gatsby","Netlify","Zapier","RSS","gatsby-plugin-feed"]}}},{"node":{"fields":{"tags":["Java","Kotlin","JJUG CCC","イベントレポート"]}}},{"node":{"fields":{"tags":["Windows","ランチャー"]}}},{"node":{"fields":{"tags":["Gatsby","Gatsby theme"]}}},{"node":{"fields":{"tags":["勉強会","LT","mdx-deck","mdx","code-surfer","markdown","プレゼン","スライド"]}}},{"node":{"fields":{"tags":["GraphQL","Nuxt.js","Apollo Client","Vue.js"]}}},{"node":{"fields":{"tags":["Gatsby","kuromoji.js","d3.js","d3Cloud","形態素解析","データ可視化","WordCloud"]}}},{"node":{"fields":{"tags":["Node.js","kuromoji.js","d3.js","d3Cloud","データ可視化","形態素解析","WordCloud"]}}},{"node":{"fields":{"tags":["React","kuromoji.js","d3.js","d3Cloud","データ可視化","形態素解析","WordCloud"]}}},{"node":{"fields":{"tags":["Gatsby","GatsbyPlugin"]}}}]},"allQiitaTags":{"edges":[{"node":{"fields":{"tags":["npm","github-pages","webpack","React","babel","Qiita"]}}},{"node":{"fields":{"tags":["Angular","angular-cli","ngrx","Angular6","Qiita"]}}},{"node":{"fields":{"tags":["JavaScript","chrome-extension","Docker","GitBucket","Qiita"]}}},{"node":{"fields":{"tags":["JavaScript","GitHub","TypeScript","chrome-extension","Qiita"]}}},{"node":{"fields":{"tags":["JavaScript","Node.js","Express","mongoose","Angular","Qiita"]}}},{"node":{"fields":{"tags":["JavaScript","jasmine","TypeScript","Angular","Protractor","Qiita"]}}},{"node":{"fields":{"tags":["JavaScript","MongoDB","Express","TypeScript","Angular","Qiita"]}}},{"node":{"fields":{"tags":["JavaScript","全文検索","ドキュメント","Fess","asciidoctor","Qiita"]}}},{"node":{"fields":{"tags":["Jenkins","CI","Pipeline","Qiita"]}}},{"node":{"fields":{"tags":["Markdown","ドキュメント","asciidoctor","asciidoc","Qiita"]}}},{"node":{"fields":{"tags":["Java","Jenkins","CI","gradle","Pipeline","Qiita"]}}},{"node":{"fields":{"tags":["Java","java8","資格","Qiita"]}}}]}},"pageContext":{"tag":"angular-cli"}}